README.md
setup.cfg
setup.py
draytonwiser/__init__.py
draytonwiser/cloud.py
draytonwiser/device.py
draytonwiser/device_measurement.py
draytonwiser/exceptions.py
draytonwiser/heating_channel.py
draytonwiser/hotwater.py
draytonwiser/manager.py
draytonwiser/room.py
draytonwiser/schedule.py
draytonwiser/system.py
draytonwiser/wiserapi.py
python_draytonwiser_api.egg-info/PKG-INFO
python_draytonwiser_api.egg-info/SOURCES.txt
python_draytonwiser_api.egg-info/dependency_links.txt
python_draytonwiser_api.egg-info/requires.txt
python_draytonwiser_api.egg-info/top_level.txt
python_draytonwiser_api.egg-info/zip-safe